open_intent_classifier/__init__.py
open_intent_classifier/consts.py
open_intent_classifier/embedder.py
open_intent_classifier/model.py
open_intent_classifier/utils.py
open_intent_classifier-0.0.8.dist-info/METADATA
open_intent_classifier-0.0.8.dist-info/WHEEL
open_intent_classifier-0.0.8.dist-info/top_level.txt
open_intent_classifier-0.0.8.dist-info/RECORD
