Metadata-Version: 2.1
Name: open_intent_classifier
Version: 0.0.8
Summary: This library has two purposes: 1. allow to easily test semantic classification with open labels (not pre defined) for intent recognition. 2. allow to experiment with different n-shot classification components.
Home-page: https://github.com/SerjSmor/open-intent-classifier
Author: Serj Smorodinsky
Author-email: serjsmor@gmail.com
Requires-Dist: transformers
Requires-Dist: torch
Requires-Dist: sentencepiece
Requires-Dist: scikit-learn
Requires-Dist: sentence-transformers
Requires-Dist: pandas
Requires-Dist: python-dotenv
Requires-Dist: openai
Requires-Dist: dspy
Requires-Dist: accelerate
